<?xml version="1.0" encoding="utf-8" ?>
<dwsync>
<file name="3024-day.css" server="sftp.itd.umich.edu//afs/umich.edu/group/i/itsmobap/Public/html/drupal/" local="131003013860000000" remote="131003013860000000" Dst="1" />
<file name="3024-night.css" server="sftp.itd.umich.edu//afs/umich.edu/group/i/itsmobap/Public/html/drupal/" local="131003013860000000" remote="131003013860000000" Dst="1" />
<file name="ambiance-mobile.css" server="sftp.itd.umich.edu//afs/umich.edu/group/i/itsmobap/Public/html/drupal/" local="131003013860000000" remote="131003013860000000" Dst="1" />
<file name="ambiance.css" server="sftp.itd.umich.edu//afs/umich.edu/group/i/itsmobap/Public/html/drupal/" local="131003013870000000" remote="131003013870000000" Dst="1" />
<file name="base16-dark.css" server="sftp.itd.umich.edu//afs/umich.edu/group/i/itsmobap/Public/html/drupal/" local="131003013870000000" remote="131003013870000000" Dst="1" />
<file name="base16-light.css" server="sftp.itd.umich.edu//afs/umich.edu/group/i/itsmobap/Public/html/drupal/" local="131003013870000000" remote="131003013870000000" Dst="1" />
<file name="blackboard.css" server="sftp.itd.umich.edu//afs/umich.edu/group/i/itsmobap/Public/html/drupal/" local="131003013870000000" remote="131003013870000000" Dst="1" />
<file name="cobalt.css" server="sftp.itd.umich.edu//afs/umich.edu/group/i/itsmobap/Public/html/drupal/" local="131003013910000000" remote="131003013910000000" Dst="1" />
<file name="colorforth.css" server="sftp.itd.umich.edu//afs/umich.edu/group/i/itsmobap/Public/html/drupal/" local="131003013910000000" remote="131003013910000000" Dst="1" />
<file name="eclipse.css" server="sftp.itd.umich.edu//afs/umich.edu/group/i/itsmobap/Public/html/drupal/" local="131003013920000000" remote="131003013920000000" Dst="1" />
<file name="elegant.css" server="sftp.itd.umich.edu//afs/umich.edu/group/i/itsmobap/Public/html/drupal/" local="131003013920000000" remote="131003013920000000" Dst="1" />
<file name="erlang-dark.css" server="sftp.itd.umich.edu//afs/umich.edu/group/i/itsmobap/Public/html/drupal/" local="131003013930000000" remote="131003013930000000" Dst="1" />
<file name="lesser-dark.css" server="sftp.itd.umich.edu//afs/umich.edu/group/i/itsmobap/Public/html/drupal/" local="131003013930000000" remote="131003013930000000" Dst="1" />
<file name="liquibyte.css" server="sftp.itd.umich.edu//afs/umich.edu/group/i/itsmobap/Public/html/drupal/" local="131003013930000000" remote="131003013930000000" Dst="1" />
<file name="mbo.css" server="sftp.itd.umich.edu//afs/umich.edu/group/i/itsmobap/Public/html/drupal/" local="131003013950000000" remote="131003013950000000" Dst="1" />
<file name="mdn-like.css" server="sftp.itd.umich.edu//afs/umich.edu/group/i/itsmobap/Public/html/drupal/" local="131003013950000000" remote="131003013950000000" Dst="1" />
<file name="midnight.css" server="sftp.itd.umich.edu//afs/umich.edu/group/i/itsmobap/Public/html/drupal/" local="131003013950000000" remote="131003013950000000" Dst="1" />
<file name="monokai.css" server="sftp.itd.umich.edu//afs/umich.edu/group/i/itsmobap/Public/html/drupal/" local="131003013960000000" remote="131003013960000000" Dst="1" />
<file name="neat.css" server="sftp.itd.umich.edu//afs/umich.edu/group/i/itsmobap/Public/html/drupal/" local="131003013960000000" remote="131003013960000000" Dst="1" />
<file name="neo.css" server="sftp.itd.umich.edu//afs/umich.edu/group/i/itsmobap/Public/html/drupal/" local="131003013960000000" remote="131003013960000000" Dst="1" />
<file name="night.css" server="sftp.itd.umich.edu//afs/umich.edu/group/i/itsmobap/Public/html/drupal/" local="131003013970000000" remote="131003013970000000" Dst="1" />
<file name="paraiso-dark.css" server="sftp.itd.umich.edu//afs/umich.edu/group/i/itsmobap/Public/html/drupal/" local="131003014000000000" remote="131003014000000000" Dst="1" />
<file name="paraiso-light.css" server="sftp.itd.umich.edu//afs/umich.edu/group/i/itsmobap/Public/html/drupal/" local="131003014000000000" remote="131003014000000000" Dst="1" />
<file name="pastel-on-dark.css" server="sftp.itd.umich.edu//afs/umich.edu/group/i/itsmobap/Public/html/drupal/" local="131003014010000000" remote="131003014010000000" Dst="1" />
<file name="rubyblue.css" server="sftp.itd.umich.edu//afs/umich.edu/group/i/itsmobap/Public/html/drupal/" local="131003014010000000" remote="131003014010000000" Dst="1" />
<file name="solarized.css" server="sftp.itd.umich.edu//afs/umich.edu/group/i/itsmobap/Public/html/drupal/" local="131003014020000000" remote="131003014020000000" Dst="1" />
<file name="the-matrix.css" server="sftp.itd.umich.edu//afs/umich.edu/group/i/itsmobap/Public/html/drupal/" local="131003014020000000" remote="131003014020000000" Dst="1" />
<file name="tomorrow-night-bright.css" server="sftp.itd.umich.edu//afs/umich.edu/group/i/itsmobap/Public/html/drupal/" local="131003014020000000" remote="131003014020000000" Dst="1" />
<file name="tomorrow-night-eighties.css" server="sftp.itd.umich.edu//afs/umich.edu/group/i/itsmobap/Public/html/drupal/" local="131003014060000000" remote="131003014060000000" Dst="1" />
<file name="ttcn.css" server="sftp.itd.umich.edu//afs/umich.edu/group/i/itsmobap/Public/html/drupal/" local="131003014060000000" remote="131003014060000000" Dst="1" />
<file name="twilight.css" server="sftp.itd.umich.edu//afs/umich.edu/group/i/itsmobap/Public/html/drupal/" local="131003014060000000" remote="131003014060000000" Dst="1" />
<file name="vibrant-ink.css" server="sftp.itd.umich.edu//afs/umich.edu/group/i/itsmobap/Public/html/drupal/" local="131003014060000000" remote="131003014060000000" Dst="1" />
<file name="xq-dark.css" server="sftp.itd.umich.edu//afs/umich.edu/group/i/itsmobap/Public/html/drupal/" local="131003014060000000" remote="131003014060000000" Dst="1" />
<file name="xq-light.css" server="sftp.itd.umich.edu//afs/umich.edu/group/i/itsmobap/Public/html/drupal/" local="131003014070000000" remote="131003014070000000" Dst="1" />
<file name="zenburn.css" server="sftp.itd.umich.edu//afs/umich.edu/group/i/itsmobap/Public/html/drupal/" local="131003014080000000" remote="131003014080000000" Dst="1" />
</dwsync>